Metadata-Version: 2.1
Name: vkpore
Version: 0.1.0
Summary: Library for organizing interactions with Vkontakte api.
Home-page: https://github.com/ekonda/vkpore/
Author: Michael Krukov
Author-email: krukov.michael@ya.ru
License: UNKNOWN
Keywords: library,vkontakte,asynchronous,asyncio,longpoll
Platform: UNKNOWN
Classifier: Programming Language :: Python :: 3
Classifier: Programming Language :: Python :: 3 :: Only
Classifier: Operating System :: OS Independent
Classifier: Intended Audience :: Developers
Classifier: Topic :: Software Development :: Libraries
Classifier: License :: OSI Approved :: MIT License
Requires-Python: >=3.5
